haydn/scheduler/__init__.py
haydn/scheduler/scheduler.py
job_scheduler-0.3.3.dist-info/METADATA
job_scheduler-0.3.3.dist-info/WHEEL
job_scheduler-0.3.3.dist-info/top_level.txt
job_scheduler-0.3.3.dist-info/RECORD
