Metadata-Version: 2.1
Name: job-scheduler
Version: 0.3.3
Summary: Simple Scheduler for Python 3.X
Home-page: https://bitbucket.org/haydn_team/scheduler/
Author: Jason Lee
Author-email: UNKNOWN
License: UNKNOWN
Download-URL: https://bitbucket.org/haydn_team/scheduler.git
Platform: UNKNOWN
Requires-Dist: event-emitter
